pyphase/__init__.py
pyphase/__main__.py
pyphase/config.py
pyphase/dataset.py
pyphase/parallelizer.py
pyphase/phaseretrieval.py
pyphase/propagator.py
pyphase/tomography.py
pyphase/utilities.py
vendor/EdfFile.py
vendor/__init__.py
vendor/pyelastix.py
pyphase-1.0.1.dist-info/LICENSE
pyphase-1.0.1.dist-info/METADATA
pyphase-1.0.1.dist-info/WHEEL
pyphase-1.0.1.dist-info/top_level.txt
pyphase-1.0.1.dist-info/RECORD
